muvisdk/MuviBase.py
muvisdk/SDK.py
muvisdk/__init__.py
muvisdk/decidir_sdk/Card.py
muvisdk/decidir_sdk/CardToken.py
muvisdk/decidir_sdk/Customer.py
muvisdk/decidir_sdk/DecidirSDK.py
muvisdk/decidir_sdk/Payment.py
muvisdk/decidir_sdk/Refund.py
muvisdk/decidir_sdk/__init__.py
muvisdk/mercadopago_sdk/Card.py
muvisdk/mercadopago_sdk/CardToken.py
muvisdk/mercadopago_sdk/Customer.py
muvisdk/mercadopago_sdk/MercadoPagoSDK.py
muvisdk/mercadopago_sdk/Payment.py
muvisdk/mercadopago_sdk/Refund.py
muvisdk/mercadopago_sdk/__init__.py
muvisdk-0.0.91.dist-info/METADATA
muvisdk-0.0.91.dist-info/WHEEL
muvisdk-0.0.91.dist-info/top_level.txt
muvisdk-0.0.91.dist-info/RECORD
