Metadata-Version: 2.1
Name: muvisdk
Version: 0.0.91
Summary: SDK for muvinai developers
Author: muvinai
Classifier: Programming Language :: Python :: 3
Classifier: Operating System :: OS Independent
Requires-Python: >=3.6
Requires-Dist: mercadopago
Requires-Dist: iso8601
Requires-Dist: pytz
